azcam_app/__init__.py
azcam_app/__main__.py
azcam_app/ipython_config.py
azcam_app/optimize.py
azcam_app-26.0.0.dist-info/entry_points.txt
azcam_app-26.0.0.dist-info/licenses/LICENSE
azcam_app-26.0.0.dist-info/WHEEL
azcam_app-26.0.0.dist-info/METADATA
azcam_app-26.0.0.dist-info/RECORD
