Metadata-Version: 2.4
Name: azcam-app
Version: 26.0.0
Summary: azcam-app package for controlling imaging systems
Keywords: imaging,astronomy,cameras
Author: Michael Lesser
Author-email: mlesser.az@gmail.com
Requires-Python: >=3.10
License-File: LICENSE
Requires-Dist: azcam
Requires-Dist: ipython
Requires-Dist: matplotlib
Project-URL: Documentation, https://mplesser.github.io/azcam-app/
Project-URL: Repository, https://github.com/mplesser/azcam-app/
